[
    {
    "fuel" : {
        "name" : "Fuel",
        "description" : "A can of fuel, should be able to used on the spacecraft.",
        "location" : "***TBD***",
        "store" : "Inventory"
    },
    "engine" : {
        "name" : "Engine",
        "description" : "The engine fell off from the spacecraft during the crash.",
        "location" : "***TBD***",
        "store" : "Inventory"
    },
    "bio_suit" : {
        "name" : "Bio Suit",
        "description" : "A hazmat suit, consists of an impermeable whole-body garment worn as protection against hazardous materials.",
        "location" : "***Required to enter Chap 4***",
        "defense" : 1,
        "store" : "Wear"
    },
    "TM" : {
        "name" : "TM 11-2F-35AV3",
        "description" : "This is the Technical Manual of the spacecraft, maybe I could use it to find out how to fix the spacecraft.",
        "location" : "***TBD, should be in the same place when player start***",
        "store" : "Inventory"
    },
    "keycard" : {
        "name" : "Keycard",
        "description" : "A key card, it has a symbol look the same with the one on the door of the server room.",
        "location" : "***TBD***",
        "store" : "Inventory"
    },
    "basement_key" : {
        "name" : "Metal Key",
        "description" : "An old metal key, covered with dust.",
        "location" : "***TBD***",
        "store" : "Inventory"
    },
    "toolkit" : {
        "name" : "Toolkit",
        "description" : "It is an OEM \"QuickFix\" toolkit, it fell off from the spacecraft.",
        "location" : "***TBD***",
        "store" : "Inventory"
    },
    "GPS" : {
        "name" : "GPS",
        "description" : "This thing looks like a GPS, let's see what it does",
        "location" : "***TBD***",
        "store" : "Inventory"
    },
    "knife" : {
        "name" : "Knife",
        "description" : "A cooking knife.",
        "location" : "***TBD should be at the first location***",
        "power" : 1,
        "defense" : 0,
        "store" : "Carry"
    },
    "rifle" : {
        "name" : "Rifle",
        "description" : "A rifle with an empty magazine. Fairly new condition.",
        "power" : 2,
        "defense" : 1,
        "location" : "***TBD***",
        "store" : "Carry"
    },
    "laser_gun" : {
        "name" : "Laser Gun",
        "description" : "A laser gun, nothing in the magazine well, looks like a battery pack could fit in there.",
        "power" : 3,
        "defense" : 1,
        "location" : "***TBD***",
        "store" : "Carry"
    },
    "IMTV" : {
        "name" : "IMTV",
        "description" : "Improved Modular Tactical Vest, it's always good to have a body armor on.",
        "defense" : 10,
        "location" : "***TBD***",
        "store" : "Wear"
    },
    "ACH" : {
        "name" : "ACH",
        "description" : "It's not just a helmet, it is an Advanced Combat Helmet, made of Kevlar.",
        "defense" : 5,
        "location" : "***TBD***",
        "store" : "Wear"
    },
    "gloves" : {
        "name" : "Gloves",
        "description" : "A pair of tactical gloves.",
        "defense" : 1,
        "location" : "***TBD***",
        "store" : "Wear"
    },
    "boots" : {
        "name" : "Boots",
        "description" : "A pair of tactical boots, brand new.",
        "defense" : 1,
        "location" : "***TBD***",
        "store" : "Wear"
    }
}
]